<annotation>
	<folder>data</folder>
	<filename>2019v200023.jpg</filename>
	<path>/home/wanglin/Datasets/URPC/train_data/data/2019v200023.jpg</path>
	<source>
		<database>Unknown</database>
	</source>
	<size>
		<width>3840</width>
		<height>2160</height>
		<depth>3</depth>
	</size>
	<segmented>0</segmented>
	<object>
		<name>holothurian</name>
		<pose>Unspecified</pose>
		<truncated>0</truncated>
		<difficult>0</difficult>
		<bndbox>
			<xmin>3039</xmin>
			<ymin>1005</ymin>
			<xmax>3240</xmax>
			<ymax>1181</ymax>
		</bndbox>
	</object>
	<object>
		<name>starfish</name>
		<pose>Unspecified</pose>
		<truncated>0</truncated>
		<difficult>0</difficult>
		<bndbox>
			<xmin>7</xmin>
			<ymin>1806</ymin>
			<xmax>144</xmax>
			<ymax>1996</ymax>
		</bndbox>
	</object>
	<object>
		<name>echinus</name>
		<pose>Unspecified</pose>
		<truncated>0</truncated>
		<difficult>0</difficult>
		<bndbox>
			<xmin>1608</xmin>
			<ymin>1578</ymin>
			<xmax>1848</xmax>
			<ymax>1840</ymax>
		</bndbox>
	</object>
	<object>
		<name>holothurian</name>
		<pose>Unspecified</pose>
		<truncated>0</truncated>
		<difficult>0</difficult>
		<bndbox>
			<xmin>1796</xmin>
			<ymin>1843</ymin>
			<xmax>2041</xmax>
			<ymax>2019</ymax>
		</bndbox>
	</object>
	<object>
		<name>echinus</name>
		<pose>Unspecified</pose>
		<truncated>1</truncated>
		<difficult>0</difficult>
		<bndbox>
			<xmin>1776</xmin>
			<ymin>1957</ymin>
			<xmax>2029</xmax>
			<ymax>2160</ymax>
		</bndbox>
	</object>
	<object>
		<name>holothurian</name>
		<pose>Unspecified</pose>
		<truncated>0</truncated>
		<difficult>0</difficult>
		<bndbox>
			<xmin>1702</xmin>
			<ymin>1057</ymin>
			<xmax>1811</xmax>
			<ymax>1164</ymax>
		</bndbox>
	</object>
	<object>
		<name>holothurian</name>
		<pose>Unspecified</pose>
		<truncated>0</truncated>
		<difficult>0</difficult>
		<bndbox>
			<xmin>1863</xmin>
			<ymin>879</ymin>
			<xmax>2054</xmax>
			<ymax>991</ymax>
		</bndbox>
	</object>
	<object>
		<name>holothurian</name>
		<pose>Unspecified</pose>
		<truncated>0</truncated>
		<difficult>0</difficult>
		<bndbox>
			<xmin>1360</xmin>
			<ymin>610</ymin>
			<xmax>1552</xmax>
			<ymax>726</ymax>
		</bndbox>
	</object>
	<object>
		<name>holothurian</name>
		<pose>Unspecified</pose>
		<truncated>0</truncated>
		<difficult>0</difficult>
		<bndbox>
			<xmin>1469</xmin>
			<ymin>411</ymin>
			<xmax>1593</xmax>
			<ymax>500</ymax>
		</bndbox>
	</object>
	<object>
		<name>holothurian</name>
		<pose>Unspecified</pose>
		<truncated>0</truncated>
		<difficult>0</difficult>
		<bndbox>
			<xmin>1665</xmin>
			<ymin>267</ymin>
			<xmax>1774</xmax>
			<ymax>389</ymax>
		</bndbox>
	</object>
	<object>
		<name>scallop</name>
		<pose>Unspecified</pose>
		<truncated>0</truncated>
		<difficult>0</difficult>
		<bndbox>
			<xmin>1192</xmin>
			<ymin>1223</ymin>
			<xmax>1338</xmax>
			<ymax>1342</ymax>
		</bndbox>
	</object>
	<object>
		<name>holothurian</name>
		<pose>Unspecified</pose>
		<truncated>0</truncated>
		<difficult>0</difficult>
		<bndbox>
			<xmin>1078</xmin>
			<ymin>1392</ymin>
			<xmax>1174</xmax>
			<ymax>1630</ymax>
		</bndbox>
	</object>
	<object>
		<name>scallop</name>
		<pose>Unspecified</pose>
		<truncated>0</truncated>
		<difficult>0</difficult>
		<bndbox>
			<xmin>1741</xmin>
			<ymin>572</ymin>
			<xmax>1865</xmax>
			<ymax>678</ymax>
		</bndbox>
	</object>
	<object>
		<name>starfish</name>
		<pose>Unspecified</pose>
		<truncated>0</truncated>
		<difficult>0</difficult>
		<bndbox>
			<xmin>2341</xmin>
			<ymin>116</ymin>
			<xmax>2542</xmax>
			<ymax>282</ymax>
		</bndbox>
	</object>
	<object>
		<name>scallop</name>
		<pose>Unspecified</pose>
		<truncated>0</truncated>
		<difficult>0</difficult>
		<bndbox>
			<xmin>2665</xmin>
			<ymin>7</ymin>
			<xmax>2752</xmax>
			<ymax>82</ymax>
		</bndbox>
	</object>
</annotation>
