<annotation>
	<folder>data</folder>
	<filename>2019v200521.jpg</filename>
	<path>/home/wanglin/Datasets/URPC/train_data/data/2019v200521.jpg</path>
	<source>
		<database>Unknown</database>
	</source>
	<size>
		<width>3840</width>
		<height>2160</height>
		<depth>3</depth>
	</size>
	<segmented>0</segmented>
	<object>
		<name>scallop</name>
		<pose>Unspecified</pose>
		<truncated>0</truncated>
		<difficult>0</difficult>
		<bndbox>
			<xmin>1571</xmin>
			<ymin>1368</ymin>
			<xmax>1831</xmax>
			<ymax>1578</ymax>
		</bndbox>
	</object>
	<object>
		<name>scallop</name>
		<pose>Unspecified</pose>
		<truncated>0</truncated>
		<difficult>0</difficult>
		<bndbox>
			<xmin>2089</xmin>
			<ymin>1579</ymin>
			<xmax>2340</xmax>
			<ymax>1829</ymax>
		</bndbox>
	</object>
</annotation>
