<annotation>
	<folder>data</folder>
	<filename>2019v201086.jpg</filename>
	<path>/home/wanglin/Datasets/URPC/train_data/data/2019v201086.jpg</path>
	<source>
		<database>Unknown</database>
	</source>
	<size>
		<width>3840</width>
		<height>2160</height>
		<depth>3</depth>
	</size>
	<segmented>0</segmented>
	<object>
		<name>holothurian</name>
		<pose>Unspecified</pose>
		<truncated>0</truncated>
		<difficult>0</difficult>
		<bndbox>
			<xmin>1412</xmin>
			<ymin>871</ymin>
			<xmax>1642</xmax>
			<ymax>999</ymax>
		</bndbox>
	</object>
	<object>
		<name>scallop</name>
		<pose>Unspecified</pose>
		<truncated>0</truncated>
		<difficult>0</difficult>
		<bndbox>
			<xmin>2418</xmin>
			<ymin>506</ymin>
			<xmax>2544</xmax>
			<ymax>629</ymax>
		</bndbox>
	</object>
	<object>
		<name>scallop</name>
		<pose>Unspecified</pose>
		<truncated>0</truncated>
		<difficult>0</difficult>
		<bndbox>
			<xmin>2812</xmin>
			<ymin>535</ymin>
			<xmax>2936</xmax>
			<ymax>619</ymax>
		</bndbox>
	</object>
	<object>
		<name>scallop</name>
		<pose>Unspecified</pose>
		<truncated>0</truncated>
		<difficult>0</difficult>
		<bndbox>
			<xmin>2</xmin>
			<ymin>1321</ymin>
			<xmax>208</xmax>
			<ymax>1537</ymax>
		</bndbox>
	</object>
	<object>
		<name>scallop</name>
		<pose>Unspecified</pose>
		<truncated>0</truncated>
		<difficult>0</difficult>
		<bndbox>
			<xmin>968</xmin>
			<ymin>1089</ymin>
			<xmax>1333</xmax>
			<ymax>1315</ymax>
		</bndbox>
	</object>
	<object>
		<name>scallop</name>
		<pose>Unspecified</pose>
		<truncated>0</truncated>
		<difficult>0</difficult>
		<bndbox>
			<xmin>1308</xmin>
			<ymin>1184</ymin>
			<xmax>1448</xmax>
			<ymax>1315</ymax>
		</bndbox>
	</object>
	<object>
		<name>scallop</name>
		<pose>Unspecified</pose>
		<truncated>0</truncated>
		<difficult>0</difficult>
		<bndbox>
			<xmin>1448</xmin>
			<ymin>1324</ymin>
			<xmax>1724</xmax>
			<ymax>1533</ymax>
		</bndbox>
	</object>
	<object>
		<name>scallop</name>
		<pose>Unspecified</pose>
		<truncated>0</truncated>
		<difficult>0</difficult>
		<bndbox>
			<xmin>1286</xmin>
			<ymin>1679</ymin>
			<xmax>1469</xmax>
			<ymax>1901</ymax>
		</bndbox>
	</object>
	<object>
		<name>scallop</name>
		<pose>Unspecified</pose>
		<truncated>1</truncated>
		<difficult>0</difficult>
		<bndbox>
			<xmin>2395</xmin>
			<ymin>1977</ymin>
			<xmax>2810</xmax>
			<ymax>2160</ymax>
		</bndbox>
	</object>
	<object>
		<name>scallop</name>
		<pose>Unspecified</pose>
		<truncated>0</truncated>
		<difficult>0</difficult>
		<bndbox>
			<xmin>2568</xmin>
			<ymin>1407</ymin>
			<xmax>2902</xmax>
			<ymax>1719</ymax>
		</bndbox>
	</object>
	<object>
		<name>scallop</name>
		<pose>Unspecified</pose>
		<truncated>0</truncated>
		<difficult>0</difficult>
		<bndbox>
			<xmin>2950</xmin>
			<ymin>1616</ymin>
			<xmax>3326</xmax>
			<ymax>1951</ymax>
		</bndbox>
	</object>
	<object>
		<name>scallop</name>
		<pose>Unspecified</pose>
		<truncated>1</truncated>
		<difficult>0</difficult>
		<bndbox>
			<xmin>3339</xmin>
			<ymin>1853</ymin>
			<xmax>3840</xmax>
			<ymax>2160</ymax>
		</bndbox>
	</object>
	<object>
		<name>scallop</name>
		<pose>Unspecified</pose>
		<truncated>0</truncated>
		<difficult>0</difficult>
		<bndbox>
			<xmin>3271</xmin>
			<ymin>1064</ymin>
			<xmax>3524</xmax>
			<ymax>1248</ymax>
		</bndbox>
	</object>
	<object>
		<name>scallop</name>
		<pose>Unspecified</pose>
		<truncated>0</truncated>
		<difficult>0</difficult>
		<bndbox>
			<xmin>3444</xmin>
			<ymin>1082</ymin>
			<xmax>3773</xmax>
			<ymax>1322</ymax>
		</bndbox>
	</object>
	<object>
		<name>scallop</name>
		<pose>Unspecified</pose>
		<truncated>0</truncated>
		<difficult>0</difficult>
		<bndbox>
			<xmin>3159</xmin>
			<ymin>1127</ymin>
			<xmax>3357</xmax>
			<ymax>1277</ymax>
		</bndbox>
	</object>
	<object>
		<name>scallop</name>
		<pose>Unspecified</pose>
		<truncated>0</truncated>
		<difficult>0</difficult>
		<bndbox>
			<xmin>2264</xmin>
			<ymin>1164</ymin>
			<xmax>2475</xmax>
			<ymax>1278</ymax>
		</bndbox>
	</object>
	<object>
		<name>scallop</name>
		<pose>Unspecified</pose>
		<truncated>0</truncated>
		<difficult>0</difficult>
		<bndbox>
			<xmin>2369</xmin>
			<ymin>969</ymin>
			<xmax>2586</xmax>
			<ymax>1092</ymax>
		</bndbox>
	</object>
	<object>
		<name>scallop</name>
		<pose>Unspecified</pose>
		<truncated>0</truncated>
		<difficult>0</difficult>
		<bndbox>
			<xmin>2766</xmin>
			<ymin>1087</ymin>
			<xmax>2950</xmax>
			<ymax>1246</ymax>
		</bndbox>
	</object>
	<object>
		<name>scallop</name>
		<pose>Unspecified</pose>
		<truncated>0</truncated>
		<difficult>0</difficult>
		<bndbox>
			<xmin>2417</xmin>
			<ymin>643</ymin>
			<xmax>2584</xmax>
			<ymax>752</ymax>
		</bndbox>
	</object>
	<object>
		<name>scallop</name>
		<pose>Unspecified</pose>
		<truncated>0</truncated>
		<difficult>0</difficult>
		<bndbox>
			<xmin>1628</xmin>
			<ymin>899</ymin>
			<xmax>1813</xmax>
			<ymax>987</ymax>
		</bndbox>
	</object>
	<object>
		<name>scallop</name>
		<pose>Unspecified</pose>
		<truncated>0</truncated>
		<difficult>0</difficult>
		<bndbox>
			<xmin>1869</xmin>
			<ymin>675</ymin>
			<xmax>2034</xmax>
			<ymax>761</ymax>
		</bndbox>
	</object>
	<object>
		<name>scallop</name>
		<pose>Unspecified</pose>
		<truncated>0</truncated>
		<difficult>0</difficult>
		<bndbox>
			<xmin>1654</xmin>
			<ymin>632</ymin>
			<xmax>1845</xmax>
			<ymax>723</ymax>
		</bndbox>
	</object>
	<object>
		<name>scallop</name>
		<pose>Unspecified</pose>
		<truncated>0</truncated>
		<difficult>0</difficult>
		<bndbox>
			<xmin>1708</xmin>
			<ymin>719</ymin>
			<xmax>1853</xmax>
			<ymax>817</ymax>
		</bndbox>
	</object>
</annotation>
