<annotation>
	<folder>data</folder>
	<filename>2019v100126.jpg</filename>
	<path>/home/wanglin/Datasets/URPC/train_data/data/2019v100126.jpg</path>
	<source>
		<database>Unknown</database>
	</source>
	<size>
		<width>3840</width>
		<height>2160</height>
		<depth>3</depth>
	</size>
	<segmented>0</segmented>
	<object>
		<name>scallop</name>
		<pose>Unspecified</pose>
		<truncated>0</truncated>
		<difficult>0</difficult>
		<bndbox>
			<xmin>681</xmin>
			<ymin>1070</ymin>
			<xmax>1054</xmax>
			<ymax>1220</ymax>
		</bndbox>
	</object>
	<object>
		<name>starfish</name>
		<pose>Unspecified</pose>
		<truncated>0</truncated>
		<difficult>0</difficult>
		<bndbox>
			<xmin>1913</xmin>
			<ymin>1568</ymin>
			<xmax>2138</xmax>
			<ymax>1768</ymax>
		</bndbox>
	</object>
	<object>
		<name>starfish</name>
		<pose>Unspecified</pose>
		<truncated>0</truncated>
		<difficult>0</difficult>
		<bndbox>
			<xmin>1901</xmin>
			<ymin>1412</ymin>
			<xmax>2130</xmax>
			<ymax>1577</ymax>
		</bndbox>
	</object>
	<object>
		<name>starfish</name>
		<pose>Unspecified</pose>
		<truncated>0</truncated>
		<difficult>0</difficult>
		<bndbox>
			<xmin>1701</xmin>
			<ymin>1624</ymin>
			<xmax>1911</xmax>
			<ymax>1902</ymax>
		</bndbox>
	</object>
</annotation>
