<annotation>
	<folder>data</folder>
	<filename>CHN083846_0658.jpg</filename>
	<path>/home/wanglin/Datasets/URPC/train_data/data/CHN083846_0658.jpg</path>
	<source>
		<database>Unknown</database>
	</source>
	<size>
		<width>704</width>
		<height>576</height>
		<depth>3</depth>
	</size>
	<segmented>0</segmented>
	<object>
		<name>echinus</name>
		<pose>Unspecified</pose>
		<truncated>0</truncated>
		<difficult>0</difficult>
		<bndbox>
			<xmin>129</xmin>
			<ymin>104</ymin>
			<xmax>187</xmax>
			<ymax>166</ymax>
		</bndbox>
	</object>
	<object>
		<name>echinus</name>
		<pose>Unspecified</pose>
		<truncated>0</truncated>
		<difficult>0</difficult>
		<bndbox>
			<xmin>553</xmin>
			<ymin>494</ymin>
			<xmax>619</xmax>
			<ymax>571</ymax>
		</bndbox>
	</object>
	<object>
		<name>echinus</name>
		<pose>Unspecified</pose>
		<truncated>0</truncated>
		<difficult>0</difficult>
		<bndbox>
			<xmin>377</xmin>
			<ymin>397</ymin>
			<xmax>449</xmax>
			<ymax>461</ymax>
		</bndbox>
	</object>
</annotation>
