<annotation>
	<folder>data</folder>
	<filename>GOPR0293_9543.jpg</filename>
	<path>/home/wanglin/Datasets/URPC/train_data/data/GOPR0293_9543.jpg</path>
	<source>
		<database>Unknown</database>
	</source>
	<size>
		<width>1920</width>
		<height>1080</height>
		<depth>3</depth>
	</size>
	<segmented>0</segmented>
	<object>
		<name>echinus</name>
		<pose>Unspecified</pose>
		<truncated>0</truncated>
		<difficult>0</difficult>
		<bndbox>
			<xmin>1227</xmin>
			<ymin>163</ymin>
			<xmax>1285</xmax>
			<ymax>231</ymax>
		</bndbox>
	</object>
	<object>
		<name>echinus</name>
		<pose>Unspecified</pose>
		<truncated>0</truncated>
		<difficult>0</difficult>
		<bndbox>
			<xmin>1130</xmin>
			<ymin>308</ymin>
			<xmax>1181</xmax>
			<ymax>367</ymax>
		</bndbox>
	</object>
	<object>
		<name>echinus</name>
		<pose>Unspecified</pose>
		<truncated>0</truncated>
		<difficult>0</difficult>
		<bndbox>
			<xmin>861</xmin>
			<ymin>59</ymin>
			<xmax>903</xmax>
			<ymax>112</ymax>
		</bndbox>
	</object>
	<object>
		<name>echinus</name>
		<pose>Unspecified</pose>
		<truncated>0</truncated>
		<difficult>0</difficult>
		<bndbox>
			<xmin>958</xmin>
			<ymin>57</ymin>
			<xmax>1026</xmax>
			<ymax>107</ymax>
		</bndbox>
	</object>
	<object>
		<name>echinus</name>
		<pose>Unspecified</pose>
		<truncated>0</truncated>
		<difficult>0</difficult>
		<bndbox>
			<xmin>2</xmin>
			<ymin>130</ymin>
			<xmax>94</xmax>
			<ymax>183</ymax>
		</bndbox>
	</object>
	<object>
		<name>echinus</name>
		<pose>Unspecified</pose>
		<truncated>0</truncated>
		<difficult>0</difficult>
		<bndbox>
			<xmin>721</xmin>
			<ymin>168</ymin>
			<xmax>768</xmax>
			<ymax>217</ymax>
		</bndbox>
	</object>
	<object>
		<name>echinus</name>
		<pose>Unspecified</pose>
		<truncated>1</truncated>
		<difficult>0</difficult>
		<bndbox>
			<xmin>506</xmin>
			<ymin>971</ymin>
			<xmax>618</xmax>
			<ymax>1080</ymax>
		</bndbox>
	</object>
	<object>
		<name>echinus</name>
		<pose>Unspecified</pose>
		<truncated>0</truncated>
		<difficult>0</difficult>
		<bndbox>
			<xmin>1497</xmin>
			<ymin>959</ymin>
			<xmax>1612</xmax>
			<ymax>1056</ymax>
		</bndbox>
	</object>
	<object>
		<name>echinus</name>
		<pose>Unspecified</pose>
		<truncated>0</truncated>
		<difficult>0</difficult>
		<bndbox>
			<xmin>1561</xmin>
			<ymin>515</ymin>
			<xmax>1614</xmax>
			<ymax>562</ymax>
		</bndbox>
	</object>
	<object>
		<name>echinus</name>
		<pose>Unspecified</pose>
		<truncated>0</truncated>
		<difficult>0</difficult>
		<bndbox>
			<xmin>666</xmin>
			<ymin>502</ymin>
			<xmax>761</xmax>
			<ymax>589</ymax>
		</bndbox>
	</object>
	<object>
		<name>echinus</name>
		<pose>Unspecified</pose>
		<truncated>0</truncated>
		<difficult>0</difficult>
		<bndbox>
			<xmin>1003</xmin>
			<ymin>173</ymin>
			<xmax>1096</xmax>
			<ymax>243</ymax>
		</bndbox>
	</object>
	<object>
		<name>holothurian</name>
		<pose>Unspecified</pose>
		<truncated>0</truncated>
		<difficult>0</difficult>
		<bndbox>
			<xmin>1214</xmin>
			<ymin>294</ymin>
			<xmax>1311</xmax>
			<ymax>375</ymax>
		</bndbox>
	</object>
</annotation>
