<annotation>
	<folder>data</folder>
	<filename>GOPR0293_18316.jpg</filename>
	<path>/home/wanglin/Datasets/URPC/train_data/data/GOPR0293_18316.jpg</path>
	<source>
		<database>Unknown</database>
	</source>
	<size>
		<width>1920</width>
		<height>1080</height>
		<depth>3</depth>
	</size>
	<segmented>0</segmented>
	<object>
		<name>holothurian</name>
		<pose>Unspecified</pose>
		<truncated>0</truncated>
		<difficult>0</difficult>
		<bndbox>
			<xmin>1473</xmin>
			<ymin>475</ymin>
			<xmax>1588</xmax>
			<ymax>752</ymax>
		</bndbox>
	</object>
	<object>
		<name>echinus</name>
		<pose>Unspecified</pose>
		<truncated>0</truncated>
		<difficult>0</difficult>
		<bndbox>
			<xmin>382</xmin>
			<ymin>74</ymin>
			<xmax>484</xmax>
			<ymax>165</ymax>
		</bndbox>
	</object>
	<object>
		<name>echinus</name>
		<pose>Unspecified</pose>
		<truncated>0</truncated>
		<difficult>0</difficult>
		<bndbox>
			<xmin>800</xmin>
			<ymin>802</ymin>
			<xmax>927</xmax>
			<ymax>928</ymax>
		</bndbox>
	</object>
</annotation>
