<annotation>
	<folder>data</folder>
	<filename>YDXJ0002_8636.jpg</filename>
	<path>/home/wanglin/Datasets/URPC/train_data/data/YDXJ0002_8636.jpg</path>
	<source>
		<database>Unknown</database>
	</source>
	<size>
		<width>720</width>
		<height>405</height>
		<depth>3</depth>
	</size>
	<segmented>0</segmented>
	<object>
		<name>starfish</name>
		<pose>Unspecified</pose>
		<truncated>1</truncated>
		<difficult>0</difficult>
		<bndbox>
			<xmin>395</xmin>
			<ymin>1</ymin>
			<xmax>438</xmax>
			<ymax>47</ymax>
		</bndbox>
	</object>
	<object>
		<name>starfish</name>
		<pose>Unspecified</pose>
		<truncated>0</truncated>
		<difficult>0</difficult>
		<bndbox>
			<xmin>119</xmin>
			<ymin>183</ymin>
			<xmax>182</xmax>
			<ymax>254</ymax>
		</bndbox>
	</object>
	<object>
		<name>starfish</name>
		<pose>Unspecified</pose>
		<truncated>0</truncated>
		<difficult>0</difficult>
		<bndbox>
			<xmin>373</xmin>
			<ymin>135</ymin>
			<xmax>426</xmax>
			<ymax>201</ymax>
		</bndbox>
	</object>
	<object>
		<name>starfish</name>
		<pose>Unspecified</pose>
		<truncated>0</truncated>
		<difficult>0</difficult>
		<bndbox>
			<xmin>185</xmin>
			<ymin>319</ymin>
			<xmax>231</xmax>
			<ymax>361</ymax>
		</bndbox>
	</object>
	<object>
		<name>echinus</name>
		<pose>Unspecified</pose>
		<truncated>1</truncated>
		<difficult>0</difficult>
		<bndbox>
			<xmin>678</xmin>
			<ymin>85</ymin>
			<xmax>720</xmax>
			<ymax>168</ymax>
		</bndbox>
	</object>
	<object>
		<name>echinus</name>
		<pose>Unspecified</pose>
		<truncated>1</truncated>
		<difficult>0</difficult>
		<bndbox>
			<xmin>427</xmin>
			<ymin>1</ymin>
			<xmax>504</xmax>
			<ymax>81</ymax>
		</bndbox>
	</object>
</annotation>
