<annotation>
	<folder>data</folder>
	<filename>YDXJ0001_9620.jpg</filename>
	<path>/home/wanglin/Datasets/URPC/train_data/data/YDXJ0001_9620.jpg</path>
	<source>
		<database>Unknown</database>
	</source>
	<size>
		<width>720</width>
		<height>405</height>
		<depth>3</depth>
	</size>
	<segmented>0</segmented>
	<object>
		<name>echinus</name>
		<pose>Unspecified</pose>
		<truncated>0</truncated>
		<difficult>0</difficult>
		<bndbox>
			<xmin>536</xmin>
			<ymin>84</ymin>
			<xmax>582</xmax>
			<ymax>140</ymax>
		</bndbox>
	</object>
	<object>
		<name>echinus</name>
		<pose>Unspecified</pose>
		<truncated>0</truncated>
		<difficult>0</difficult>
		<bndbox>
			<xmin>4</xmin>
			<ymin>219</ymin>
			<xmax>190</xmax>
			<ymax>396</ymax>
		</bndbox>
	</object>
	<object>
		<name>echinus</name>
		<pose>Unspecified</pose>
		<truncated>1</truncated>
		<difficult>0</difficult>
		<bndbox>
			<xmin>596</xmin>
			<ymin>1</ymin>
			<xmax>664</xmax>
			<ymax>34</ymax>
		</bndbox>
	</object>
	<object>
		<name>holothurian</name>
		<pose>Unspecified</pose>
		<truncated>1</truncated>
		<difficult>0</difficult>
		<bndbox>
			<xmin>1</xmin>
			<ymin>1</ymin>
			<xmax>78</xmax>
			<ymax>112</ymax>
		</bndbox>
	</object>
	<object>
		<name>holothurian</name>
		<pose>Unspecified</pose>
		<truncated>1</truncated>
		<difficult>0</difficult>
		<bndbox>
			<xmin>1</xmin>
			<ymin>165</ymin>
			<xmax>125</xmax>
			<ymax>275</ymax>
		</bndbox>
	</object>
</annotation>
