<annotation>
	<folder>data</folder>
	<filename>YN010001_6761.jpg</filename>
	<path>/home/wanglin/Datasets/URPC/train_data/data/YN010001_6761.jpg</path>
	<source>
		<database>Unknown</database>
	</source>
	<size>
		<width>720</width>
		<height>405</height>
		<depth>3</depth>
	</size>
	<segmented>0</segmented>
	<object>
		<name>echinus</name>
		<pose>Unspecified</pose>
		<truncated>0</truncated>
		<difficult>0</difficult>
		<bndbox>
			<xmin>671</xmin>
			<ymin>76</ymin>
			<xmax>696</xmax>
			<ymax>101</ymax>
		</bndbox>
	</object>
	<object>
		<name>echinus</name>
		<pose>Unspecified</pose>
		<truncated>0</truncated>
		<difficult>0</difficult>
		<bndbox>
			<xmin>671</xmin>
			<ymin>110</ymin>
			<xmax>695</xmax>
			<ymax>134</ymax>
		</bndbox>
	</object>
	<object>
		<name>starfish</name>
		<pose>Unspecified</pose>
		<truncated>0</truncated>
		<difficult>0</difficult>
		<bndbox>
			<xmin>670</xmin>
			<ymin>264</ymin>
			<xmax>714</xmax>
			<ymax>312</ymax>
		</bndbox>
	</object>
	<object>
		<name>starfish</name>
		<pose>Unspecified</pose>
		<truncated>0</truncated>
		<difficult>0</difficult>
		<bndbox>
			<xmin>468</xmin>
			<ymin>225</ymin>
			<xmax>517</xmax>
			<ymax>264</ymax>
		</bndbox>
	</object>
	<object>
		<name>echinus</name>
		<pose>Unspecified</pose>
		<truncated>0</truncated>
		<difficult>0</difficult>
		<bndbox>
			<xmin>375</xmin>
			<ymin>92</ymin>
			<xmax>487</xmax>
			<ymax>191</ymax>
		</bndbox>
	</object>
</annotation>
