<?xml version="1.0" encoding="utf-8"?>
<annotation>
   <filename>YN010001_12471</filename>
   <object>
      <name>holothurian</name>
      <bndbox>
         <xmin>333</xmin>
         <ymin>223</ymin>
         <xmax>372</xmax>
         <ymax>278</ymax>
      </bndbox>
   </object>
   <object>
      <name>echinus</name>
      <bndbox>
         <xmin>6</xmin>
         <ymin>269</ymin>
         <xmax>98</xmax>
         <ymax>341</ymax>
      </bndbox>
   </object>
   <object>
      <name>echinus</name>
      <bndbox>
         <xmin>258</xmin>
         <ymin>335</ymin>
         <xmax>315</xmax>
         <ymax>404</ymax>
      </bndbox>
   </object>
   <object>
      <name>holothurian</name>
      <bndbox>
         <xmin>159</xmin>
         <ymin>214</ymin>
         <xmax>220</xmax>
         <ymax>245</ymax>
      </bndbox>
   </object>
   <object>
      <name>holothurian</name>
      <bndbox>
         <xmin>49</xmin>
         <ymin>180</ymin>
         <xmax>117</xmax>
         <ymax>207</ymax>
      </bndbox>
   </object>
</annotation>