<annotation>
	<folder>data</folder>
	<filename>YN020001_9315.jpg</filename>
	<path>/home/wanglin/Datasets/URPC/train_data/data/YN020001_9315.jpg</path>
	<source>
		<database>Unknown</database>
	</source>
	<size>
		<width>720</width>
		<height>405</height>
		<depth>3</depth>
	</size>
	<segmented>0</segmented>
	<object>
		<name>starfish</name>
		<pose>Unspecified</pose>
		<truncated>0</truncated>
		<difficult>0</difficult>
		<bndbox>
			<xmin>24</xmin>
			<ymin>183</ymin>
			<xmax>92</xmax>
			<ymax>234</ymax>
		</bndbox>
	</object>
	<object>
		<name>starfish</name>
		<pose>Unspecified</pose>
		<truncated>0</truncated>
		<difficult>0</difficult>
		<bndbox>
			<xmin>369</xmin>
			<ymin>240</ymin>
			<xmax>439</xmax>
			<ymax>294</ymax>
		</bndbox>
	</object>
	<object>
		<name>starfish</name>
		<pose>Unspecified</pose>
		<truncated>0</truncated>
		<difficult>0</difficult>
		<bndbox>
			<xmin>475</xmin>
			<ymin>56</ymin>
			<xmax>514</xmax>
			<ymax>90</ymax>
		</bndbox>
	</object>
	<object>
		<name>echinus</name>
		<pose>Unspecified</pose>
		<truncated>0</truncated>
		<difficult>0</difficult>
		<bndbox>
			<xmin>120</xmin>
			<ymin>146</ymin>
			<xmax>180</xmax>
			<ymax>191</ymax>
		</bndbox>
	</object>
	<object>
		<name>echinus</name>
		<pose>Unspecified</pose>
		<truncated>0</truncated>
		<difficult>0</difficult>
		<bndbox>
			<xmin>177</xmin>
			<ymin>205</ymin>
			<xmax>219</xmax>
			<ymax>256</ymax>
		</bndbox>
	</object>
	<object>
		<name>echinus</name>
		<pose>Unspecified</pose>
		<truncated>1</truncated>
		<difficult>0</difficult>
		<bndbox>
			<xmin>679</xmin>
			<ymin>289</ymin>
			<xmax>720</xmax>
			<ymax>342</ymax>
		</bndbox>
	</object>
	<object>
		<name>holothurian</name>
		<pose>Unspecified</pose>
		<truncated>0</truncated>
		<difficult>0</difficult>
		<bndbox>
			<xmin>602</xmin>
			<ymin>214</ymin>
			<xmax>683</xmax>
			<ymax>240</ymax>
		</bndbox>
	</object>
	<object>
		<name>holothurian</name>
		<pose>Unspecified</pose>
		<truncated>0</truncated>
		<difficult>0</difficult>
		<bndbox>
			<xmin>622</xmin>
			<ymin>242</ymin>
			<xmax>712</xmax>
			<ymax>281</ymax>
		</bndbox>
	</object>
	<object>
		<name>holothurian</name>
		<pose>Unspecified</pose>
		<truncated>0</truncated>
		<difficult>0</difficult>
		<bndbox>
			<xmin>637</xmin>
			<ymin>117</ymin>
			<xmax>666</xmax>
			<ymax>157</ymax>
		</bndbox>
	</object>
</annotation>
