<annotation>
	<folder>data</folder>
	<filename>YN030001_4291.jpg</filename>
	<path>/home/wanglin/Datasets/URPC/train_data/data/YN030001_4291.jpg</path>
	<source>
		<database>Unknown</database>
	</source>
	<size>
		<width>720</width>
		<height>405</height>
		<depth>3</depth>
	</size>
	<segmented>0</segmented>
	<object>
		<name>echinus</name>
		<pose>Unspecified</pose>
		<truncated>0</truncated>
		<difficult>0</difficult>
		<bndbox>
			<xmin>516</xmin>
			<ymin>278</ymin>
			<xmax>599</xmax>
			<ymax>360</ymax>
		</bndbox>
	</object>
	<object>
		<name>echinus</name>
		<pose>Unspecified</pose>
		<truncated>0</truncated>
		<difficult>0</difficult>
		<bndbox>
			<xmin>364</xmin>
			<ymin>260</ymin>
			<xmax>417</xmax>
			<ymax>320</ymax>
		</bndbox>
	</object>
	<object>
		<name>echinus</name>
		<pose>Unspecified</pose>
		<truncated>0</truncated>
		<difficult>0</difficult>
		<bndbox>
			<xmin>531</xmin>
			<ymin>117</ymin>
			<xmax>608</xmax>
			<ymax>196</ymax>
		</bndbox>
	</object>
	<object>
		<name>echinus</name>
		<pose>Unspecified</pose>
		<truncated>0</truncated>
		<difficult>0</difficult>
		<bndbox>
			<xmin>604</xmin>
			<ymin>64</ymin>
			<xmax>664</xmax>
			<ymax>124</ymax>
		</bndbox>
	</object>
	<object>
		<name>starfish</name>
		<pose>Unspecified</pose>
		<truncated>0</truncated>
		<difficult>0</difficult>
		<bndbox>
			<xmin>430</xmin>
			<ymin>309</ymin>
			<xmax>502</xmax>
			<ymax>382</ymax>
		</bndbox>
	</object>
	<object>
		<name>starfish</name>
		<pose>Unspecified</pose>
		<truncated>0</truncated>
		<difficult>0</difficult>
		<bndbox>
			<xmin>357</xmin>
			<ymin>326</ymin>
			<xmax>413</xmax>
			<ymax>390</ymax>
		</bndbox>
	</object>
</annotation>
